mummichog/JSON_metabolicModels.py
mummichog/__init__.py
mummichog/command_line.py
mummichog/compound_dicts.py
mummichog/config.py
mummichog/functional_analysis.py
mummichog/get_user_data.py
mummichog/ions.py
mummichog/main.py
mummichog/models.py
mummichog/ng_modularity.py
mummichog/nx_modularity.py
mummichog/reporting.py
mummichog/websnippets.py
mummichog/resources/__init__.py
mummichog/resources/plotly-graphs.js
mummichog/resources/plotly-latest.min.js
mummichog/tests/__init__.py
mummichog/tests/testdata0710.txt
mummichog-2.7.0.data/data/mummichog/resources/plotly-graphs.js
mummichog-2.7.0.data/data/mummichog/resources/plotly-latest.min.js
mummichog-2.7.0.data/data/mummichog/tests/testdata0710.txt
mummichog-2.7.0.dist-info/LICENSE
mummichog-2.7.0.dist-info/METADATA
mummichog-2.7.0.dist-info/WHEEL
mummichog-2.7.0.dist-info/entry_points.txt
mummichog-2.7.0.dist-info/top_level.txt
mummichog-2.7.0.dist-info/zip-safe
mummichog-2.7.0.dist-info/RECORD
