Metadata-Version: 2.1
Name: mummichog
Version: 2.7.0
Summary: Pathway and network analysis for metabolomics data
Home-page: https://github.com/shuzhao-li/mummichog
Author: Shuzhao Li, Francisco Castellanos, Andrei Todor
Author-email: shuzhao.li@gmail.com
License: BSD 3-Clause
Keywords: metabolomics analysis bioinformatics mass spectrometry systems biology
Classifier: Intended Audience :: Developers
Classifier: Intended Audience :: Science/Research
Classifier: License :: OSI Approved :: BSD License
Classifier: Natural Language :: English
Classifier: Operating System :: OS Independent
Classifier: Programming Language :: Python :: 3
Classifier: Topic :: Scientific/Engineering :: Bio-Informatics
Classifier: Topic :: Scientific/Engineering :: Chemistry
Classifier: Topic :: Software Development :: Libraries :: Python Modules
Requires-Python: >=3.4
License-File: LICENSE
Requires-Dist: matplotlib
Requires-Dist: networkx >=2
Requires-Dist: numpy
Requires-Dist: scipy
Requires-Dist: xlsxwriter
